smb3_video_autosplitter/autosplitter.py
smb3_video_autosplitter/livesplit.py
smb3_video_autosplitter/logging.py
smb3_video_autosplitter/main.py
smb3_video_autosplitter/opencv.py
smb3_video_autosplitter/settings.py
smb3_video_autosplitter/util.py
smb3_video_autosplitter/__init__.py
smb3_video_autosplitter-1.2.1.dist-info/METADATA
smb3_video_autosplitter-1.2.1.dist-info/metadata.json
smb3_video_autosplitter-1.2.1.dist-info/RECORD
smb3_video_autosplitter-1.2.1.dist-info/top_level.txt
smb3_video_autosplitter-1.2.1.dist-info/WHEEL
smb3_video_autosplitter-1.2.1.dist-info/zip-safe
tests/test_logging.py
tests/__init__.py
