Metadata-Version: 2.0
Name: smb3-video-autosplitter
Version: 1.2.1
Summary: Ingest video data to render smb3 eh manip stimuli
Author: narfman0
Author-email: narfman0@blastedstudios.com
License: LICENSE
Keywords: smb3-video-autosplitter
Classifier: Development Status :: 4 - Beta
Classifier: License :: OSI Approved :: GNU General Public License v3 (GPLv3)
Classifier: Operating System :: OS Independent
Classifier: Programming Language :: Python
Classifier: Topic :: Software Development :: Libraries :: Python Modules
License-File: LICENSE
Requires-Dist: dataclass-wizard
Requires-Dist: opencv-python
Requires-Dist: pygrabber
Requires-Dist: pywin32
Requires-Dist: pyyaml
